jiale0709.py
jiale0709-0.0.9.dist-info/LICENSE
jiale0709-0.0.9.dist-info/METADATA
jiale0709-0.0.9.dist-info/WHEEL
jiale0709-0.0.9.dist-info/top_level.txt
jiale0709-0.0.9.dist-info/RECORD
