Metadata-Version: 2.1
Name: jiale0709
Version: 0.0.9
Summary: Jia Le's Python Library
Author: Jia Le
Classifier: Programming Language :: Python :: 3
Classifier: License :: OSI Approved :: MIT License
Classifier: Operating System :: OS Independent
Requires-Python: >=3.6
License-File: LICENSE
